pywfp/__init__.py
pywfp/core.py
pywfp/filter_builder.py
pywfp/filter_parser.py
pywfp/wfp_engine.py
pywfp/wfp_filter.py
pywfp-0.1.42.dist-info/LICENSE
pywfp-0.1.42.dist-info/METADATA
pywfp-0.1.42.dist-info/WHEEL
pywfp-0.1.42.dist-info/top_level.txt
pywfp-0.1.42.dist-info/RECORD
