Metadata-Version: 2.2
Name: pywfp
Version: 0.1.42
Summary: A Python package for Windows Filtering Platform management
Author-email: Adrian Pitigoi <adrian.pitigoi90@gmail.com>
License: MIT
Project-URL: Homepage, https://github.com/adrianpitigoi/pywfp
Project-URL: Repository, https://github.com/adrianpitigoi/pywfp.git
Keywords: windows,filtering,network,firewall
Classifier: Development Status :: 3 - Alpha
Classifier: Intended Audience :: Developers
Classifier: License :: OSI Approved :: MIT License
Classifier: Programming Language :: Python :: 3.9
Classifier: Programming Language :: Python :: 3.10
Classifier: Programming Language :: Python :: 3.11
Classifier: Programming Language :: Python :: 3.12
Classifier: Programming Language :: Python :: 3.13
Classifier: Operating System :: Microsoft :: Windows
Requires-Python: >=3.9
License-File: LICENSE
Requires-Dist: win32more
